microservicebus-py/azure_iot_service.py
microservicebus-py/base_service.py
microservicebus-py/logger_service.py
microservicebus-py/msb_handler.py
microservicebus-py/orchestrator_service.py
microservicebus-py/queue_message.py
microservicebus-py/rauc_handler.py
microservicebus-py/start.py
microservicebus-py/test.py
microservicebus-py/utils.py
microservicebus-py/vpn_helper.py
src/axians.py
src/azure_iot_service.py
src/base_service.py
src/logger_service.py
src/msb_handler.py
src/orchestrator_service.py
src/package.json
src/queue_message.py
src/rauc_handler.py
src/start.py
src/terminal_service.py
src/test.py
src/updateMsb.py
src/update_handler.py
src/utils.py
src/vpn_helper.py
src/watchdog_service.py
microservicebus_py-1.0.18.dist-info/METADATA
microservicebus_py-1.0.18.dist-info/WHEEL
microservicebus_py-1.0.18.dist-info/entry_points.txt
microservicebus_py-1.0.18.dist-info/top_level.txt
microservicebus_py-1.0.18.dist-info/RECORD
