Metadata-Version: 2.1
Name: microservicebus-py
Version: 1.0.18
Summary: Python agent for microServiceBus.com. Please visit https://microservicebus.com for more information.
Home-page: https://github.com/axians/microservicebus-py
Author: AXIANS IoT Operations
Author-email: microservicebus@axians.com
License: MIT
Platform: UNKNOWN
Classifier: License :: OSI Approved :: MIT License
Classifier: Programming Language :: Python
Classifier: Programming Language :: Python :: 3
